account/__init__.py
account/admin.py
account/apps.py
account/forms.py
account/models.py
account/tests.py
account/urls.py
account/views.py
django_account_rcg_chandu-0.1.dist-info/LICENSE
django_account_rcg_chandu-0.1.dist-info/METADATA
django_account_rcg_chandu-0.1.dist-info/WHEEL
django_account_rcg_chandu-0.1.dist-info/top_level.txt
django_account_rcg_chandu-0.1.dist-info/RECORD
