Metadata-Version: 2.1
Name: django-account-rcg-chandu
Version: 0.1
Summary: Simple authentication for django apps
Home-page: https://github.com/rcgchandu/django-account/
Author: RCGCHANDU
Author-email: ravichandravirgo@gmail.com
License: MIT
Platform: UNKNOWN
Requires-Dist: Django (<=3.0.6,>=1.6)
